[
    {
        "round": 1,
        "score": 0.17773805074747706,
        "avg_cost": 0.0,
        "total_cost": 0.0,
        "time": "2026-02-27T14:48:49.353638"
    },
    {
        "round": 2,
        "score": 0.6458280321706904,
        "avg_cost": 0.0,
        "total_cost": 0.0,
        "time": "2026-02-27T14:49:56.428135"
    },
    {
        "round": 3,
        "score": 0.6900533276048648,
        "avg_cost": 0.0,
        "total_cost": 0.0,
        "time": "2026-02-27T14:51:03.817727"
    },
    {
        "round": 4,
        "score": 0.6489336629859076,
        "avg_cost": 0.0,
        "total_cost": 0.0,
        "time": "2026-02-27T14:52:37.508940"
    },
    {
        "round": 5,
        "score": 0.6479356378786332,
        "avg_cost": 0.0,
        "total_cost": 0.0,
        "time": "2026-02-27T14:53:47.034081"
    },
    {
        "round": 6,
        "score": 0.41273219959920726,
        "avg_cost": 0.0,
        "total_cost": 0.0,
        "time": "2026-02-27T14:58:30.271365"
    }
]